hack4u/__init__.py
hack4u/courses.py
hack4u/utils.py
adelcidplabs-0.1.0.dist-info/METADATA
adelcidplabs-0.1.0.dist-info/WHEEL
adelcidplabs-0.1.0.dist-info/top_level.txt
adelcidplabs-0.1.0.dist-info/RECORD
