Metadata-Version: 2.4
Name: adelcidplabs
Version: 0.1.0
Home-page: https://hack4u.io
Author: Asier Del Cid Pérez
Dynamic: author
Dynamic: description
Dynamic: description-content-type
Dynamic: home-page
